{
  "version": "4.0.0-beta.2",
  "flags": {},
  "shapes": [
    {
      "kie_linking": [],
      "label": "box_skill",
      "score": null,
      "points": [
        [
          3299.0425531914893,
          1917.8191489361704
        ],
        [
          3401.5957446808507,
          1917.8191489361704
        ],
        [
          3401.5957446808507,
          1971.436170212766
        ],
        [
          3299.0425531914893,
          1971.436170212766
        ]
      ],
      "group_id": null,
      "description": "",
      "difficult": false,
      "shape_type": "rectangle",
      "flags": {},
      "attributes": {}
    },
    {
      "kie_linking": [],
      "label": "box_ultimate",
      "score": null,
      "points": [
        [
          3575.3876725939626,
          1917.393617021277
        ],
        [
          3673.5106382978724,
          1917.393617021277
        ],
        [
          3673.5106382978724,
          1971.0106382978727
        ],
        [
          3575.3876725939626,
          1971.0106382978727
        ]
      ],
      "group_id": null,
      "description": "",
      "difficult": false,
      "shape_type": "rectangle",
      "flags": {},
      "attributes": {}
    },
    {
      "kie_linking": [],
      "label": "char_1_text",
      "score": null,
      "points": [
        [
          3747.2563176895305,
          483.29043002534485
        ],
        [
          3773.971119133574,
          483.29043002534485
        ],
        [
          3773.971119133574,
          515.884476534296
        ],
        [
          3747.2563176895305,
          515.884476534296
        ]
      ],
      "group_id": null,
      "description": "",
      "difficult": false,
      "shape_type": "rectangle",
      "flags": {},
      "attributes": {}
    },
    {
      "kie_linking": [],
      "label": "box_char_2",
      "score": null,
      "points": [
        [
          3573.0,
          709.9272179155901
        ],
        [
          3640.025839793281,
          709.9272179155901
        ],
        [
          3640.025839793281,
          790.0
        ],
        [
          3573.0,
          790.0
        ]
      ],
      "group_id": null,
      "description": "",
      "difficult": false,
      "shape_type": "rectangle",
      "flags": {},
      "attributes": {}
    },
    {
      "kie_linking": [],
      "label": "box_char_4",
      "score": null,
      "points": [
        [
          3573.0,
          1237.9788975021534
        ],
        [
          3638.162790697674,
          1237.9788975021534
        ],
        [
          3638.162790697674,
          1317.0
        ],
        [
          3573.0,
          1317.0
        ]
      ],
      "group_id": null,
      "description": "",
      "difficult": false,
      "shape_type": "rectangle",
      "flags": {},
      "attributes": {}
    },
    {
      "kie_linking": [],
      "label": "box_char_1",
      "score": null,
      "points": [
        [
          3573.0,
          446.75322997416026
        ],
        [
          3639.1111111111104,
          446.75322997416026
        ],
        [
          3639.1111111111104,
          526.0
        ],
        [
          3573.0,
          526.0
        ]
      ],
      "group_id": null,
      "description": "",
      "difficult": false,
      "shape_type": "rectangle",
      "flags": {},
      "attributes": {}
    },
    {
      "kie_linking": [],
      "label": "box_char_3",
      "score": null,
      "points": [
        [
          3573.0,
          974.9642549526271
        ],
        [
          3639.4220499569333,
          974.9642549526271
        ],
        [
          3639.4220499569333,
          1052.0
        ],
        [
          3573.0,
          1052.0
        ]
      ],
      "group_id": null,
      "description": "",
      "difficult": false,
      "shape_type": "rectangle",
      "flags": {},
      "attributes": {}
    },
    {
      "kie_linking": [],
      "label": "boss_lv_text",
      "score": null,
      "points": [
        [
          1647.5934579439252,
          63.36448598130853
        ],
        [
          1698.4345794392523,
          63.36448598130853
        ],
        [
          1698.4345794392523,
          111.68224299065434
        ],
        [
          1647.5934579439252,
          111.68224299065434
        ]
      ],
      "group_id": null,
      "description": "",
      "difficult": false,
      "shape_type": "rectangle",
      "flags": {},
      "attributes": {}
    },
    {
      "kie_linking": [],
      "label": "mini_map_arrow",
      "score": null,
      "points": [
        [
          290.24875621890544,
          241.39303482587073
        ],
        [
          338.8059701492537,
          241.39303482587073
        ],
        [
          338.8059701492537,
          299.10447761194035
        ],
        [
          290.24875621890544,
          299.10447761194035
        ]
      ],
      "group_id": null,
      "description": "",
      "difficult": false,
      "shape_type": "rectangle",
      "flags": {},
      "attributes": {}
    }
  ],
  "imagePath": "01.png",
  "imageData": null,
  "imageHeight": 2160,
  "imageWidth": 3840,
  "description": ""
}